{
  "basic_info": {
    "code": "000001",
    "name": "模拟基金000001",
    "type": "混合型",
    "manager": "模拟基金经理",
    "establishment_date": "2018-01-01",
    "size": 10.5,
    "rating": 4,
    "company": "模拟基金公司"
  },
  "nav_history": [
    {
      "date": "2023-12-30",
      "nav": 1.0009,
      "daily_return": 0.0008605439244708874
    },
    {
      "date": "2023-12-29",
      "nav": 0.9919,
      "daily_return": -0.008990883070722242
    },
    {
      "date": "2023-12-28",
      "nav": 0.9915,
      "daily_return": -0.00040254065749438213
    },
    {
      "date": "2023-12-27",
      "nav": 0.981,
      "daily_return": -0.010587520632805086
    },
    {
      "date": "2023-12-26",
      "nav": 0.9676,
      "daily_return": -0.013596181516679143
    },
    {
      "date": "2023-12-25",
      "nav": 0.9744,
      "daily_return": 0.006976615219264984
    },
    {
      "date": "2023-12-24",
      "nav": 0.9723,
      "daily_return": -0.0020967793805321292
    },
    {
      "date": "2023-12-23",
      "nav": 0.9749,
      "daily_return": 0.002605846512094407
    },
    {
      "date": "2023-12-22",
      "nav": 0.9925,
      "daily_return": 0.01811756317713083
    },
    {
      "date": "2023-12-21",
      "nav": 0.9914,
      "daily_return": -0.0011370565131984256
    },
    {
      "date": "2023-12-20",
      "nav": 0.9947,
      "daily_return": 0.0033563481622366585
    },
    {
      "date": "2023-12-19",
      "nav": 1.0224,
      "daily_return": 0.02786555433302687
    },
    {
      "date": "2023-12-18",
      "nav": 1.0132,
      "daily_return": -0.009020956750954011
    },
    {
      "date": "2023-12-17",
      "nav": 1.0379,
      "daily_return": 0.024348738729208903
    },
    {
      "date": "2023-12-16",
      "nav": 1.0647,
      "daily_return": 0.02579160492438265
    },
    {
      "date": "2023-12-15",
      "nav": 1.0283,
      "daily_return": -0.03416048644218606
    },
    {
      "date": "2023-12-14",
      "nav": 1.0427,
      "daily_return": 0.014000303310859094
    },
    {
      "date": "2023-12-13",
      "nav": 1.0031,
      "daily_return": -0.03797113972880889
    },
    {
      "date": "2023-12-12",
      "nav": 0.9647,
      "daily_return": -0.038315137169462256
    },
    {
      "date": "2023-12-11",
      "nav": 0.982,
      "daily_return": 0.017944387217484925
    },
    {
      "date": "2023-12-10",
      "nav": 0.9856,
      "daily_return": 0.0036924766970183294
    },
    {
      "date": "2023-12-09",
      "nav": 0.9847,
      "daily_return": -0.0009151051872826668
    },
    {
      "date": "2023-12-08",
      "nav": 0.9685,
      "daily_return": -0.016483649279513176
    },
    {
      "date": "2023-12-07",
      "nav": 0.9308,
      "daily_return": -0.03890948453560436
    },
    {
      "date": "2023-12-06",
      "nav": 0.8855,
      "daily_return": -0.04863358828160147
    },
    {
      "date": "2023-12-05",
      "nav": 0.8838,
      "daily_return": -0.0019500224405693566
    },
    {
      "date": "2023-12-04",
      "nav": 0.8761,
      "daily_return": -0.008667108550998222
    },
    {
      "date": "2023-12-03",
      "nav": 0.8798,
      "daily_return": 0.004218323034848431
    },
    {
      "date": "2023-12-02",
      "nav": 0.883,
      "daily_return": 0.003644467409219096
    },
    {
      "date": "2023-12-01",
      "nav": 0.8855,
      "daily_return": 0.0027813590581259916
    },
    {
      "date": "2023-11-30",
      "nav": 0.8495,
      "daily_return": -0.040637171498036716
    },
    {
      "date": "2023-11-29",
      "nav": 0.8891,
      "daily_return": 0.04665017944719818
    },
    {
      "date": "2023-11-28",
      "nav": 0.8676,
      "daily_return": -0.024274589765290823
    },
    {
      "date": "2023-11-27",
      "nav": 0.8873,
      "daily_return": 0.022759745695419675
    },
    {
      "date": "2023-11-26",
      "nav": 0.8867,
      "daily_return": -0.000664766244274735
    },
    {
      "date": "2023-11-25",
      "nav": 0.8903,
      "daily_return": 0.004028680807722101
    },
    {
      "date": "2023-11-24",
      "nav": 0.8724,
      "daily_return": -0.020077923314521823
    },
    {
      "date": "2023-11-23",
      "nav": 0.8702,
      "daily_return": -0.002528797009162548
    },
    {
      "date": "2023-11-22",
      "nav": 0.8907,
      "daily_return": 0.023598626035157947
    },
    {
      "date": "2023-11-21",
      "nav": 0.8792,
      "daily_return": -0.012934628823486005
    },
    {
      "date": "2023-11-20",
      "nav": 0.8704,
      "daily_return": -0.010017169496321681
    },
    {
      "date": "2023-11-19",
      "nav": 0.8626,
      "daily_return": -0.008936109810885814
    },
    {
      "date": "2023-11-18",
      "nav": 0.8549,
      "daily_return": -0.008996924067584653
    },
    {
      "date": "2023-11-17",
      "nav": 0.8673,
      "daily_return": 0.014536191246587043
    },
    {
      "date": "2023-11-16",
      "nav": 0.8293,
      "daily_return": -0.04385852811015035
    },
    {
      "date": "2023-11-15",
      "nav": 0.841,
      "daily_return": 0.014103063618585966
    },
    {
      "date": "2023-11-14",
      "nav": 0.8636,
      "daily_return": 0.026881452953034377
    },
    {
      "date": "2023-11-13",
      "nav": 0.8671,
      "daily_return": 0.004078958225733169
    },
    {
      "date": "2023-11-12",
      "nav": 0.8791,
      "daily_return": 0.013831091155037663
    },
    {
      "date": "2023-11-11",
      "nav": 0.8552,
      "daily_return": -0.0271453108940769
    },
    {
      "date": "2023-11-10",
      "nav": 0.8741,
      "daily_return": 0.02213376145296921
    },
    {
      "date": "2023-11-09",
      "nav": 0.8605,
      "daily_return": -0.015645238515061145
    },
    {
      "date": "2023-11-08",
      "nav": 0.8456,
      "daily_return": -0.017249105681472702
    },
    {
      "date": "2023-11-07",
      "nav": 0.8391,
      "daily_return": -0.007729648262013624
    },
    {
      "date": "2023-11-06",
      "nav": 0.8692,
      "daily_return": 0.03590059500453848
    },
    {
      "date": "2023-11-05",
      "nav": 0.876,
      "daily_return": 0.00776307787412903
    },
    {
      "date": "2023-11-04",
      "nav": 0.8747,
      "daily_return": -0.0014755257570585449
    },
    {
      "date": "2023-11-03",
      "nav": 0.8645,
      "daily_return": -0.011585608614585647
    },
    {
      "date": "2023-11-02",
      "nav": 0.8619,
      "daily_return": -0.0030917569299491526
    },
    {
      "date": "2023-11-01",
      "nav": 0.8542,
      "daily_return": -0.008866607117433787
    },
    {
      "date": "2023-10-30",
      "nav": 0.8697,
      "daily_return": 0.018144909848376595
    },
    {
      "date": "2023-10-29",
      "nav": 0.8727,
      "daily_return": 0.003462520391682144
    },
    {
      "date": "2023-10-28",
      "nav": 0.8529,
      "daily_return": -0.022730771910552235
    },
    {
      "date": "2023-10-27",
      "nav": 0.8583,
      "daily_return": 0.006356483310045496
    },
    {
      "date": "2023-10-26",
      "nav": 0.8677,
      "daily_return": 0.010888224023107178
    },
    {
      "date": "2023-10-25",
      "nav": 0.8566,
      "daily_return": -0.012773849973673288
    },
    {
      "date": "2023-10-24",
      "nav": 0.8415,
      "daily_return": -0.017636804529709966
    },
    {
      "date": "2023-10-23",
      "nav": 0.8588,
      "daily_return": 0.0205991050823666
    },
    {
      "date": "2023-10-22",
      "nav": 0.8618,
      "daily_return": 0.003510190446859069
    },
    {
      "date": "2023-10-21",
      "nav": 0.8868,
      "daily_return": 0.02898139533979018
    },
    {
      "date": "2023-10-20",
      "nav": 0.8916,
      "daily_return": 0.005393847084975155
    },
    {
      "date": "2023-10-19",
      "nav": 0.8764,
      "daily_return": -0.01705684023239162
    },
    {
      "date": "2023-10-18",
      "nav": 0.8668,
      "daily_return": -0.0108576651056306
    },
    {
      "date": "2023-10-17",
      "nav": 0.831,
      "daily_return": -0.04133303410091982
    },
    {
      "date": "2023-10-16",
      "nav": 0.8282,
      "daily_return": -0.0034391412938061363
    },
    {
      "date": "2023-10-15",
      "nav": 0.8266,
      "daily_return": -0.0018436014538534833
    },
    {
      "date": "2023-10-14",
      "nav": 0.8296,
      "daily_return": 0.0036182707806321434
    },
    {
      "date": "2023-10-13",
      "nav": 0.8197,
      "daily_return": -0.011976187794054936
    },
    {
      "date": "2023-10-12",
      "nav": 0.8218,
      "daily_return": 0.0025463775901755675
    },
    {
      "date": "2023-10-11",
      "nav": 0.8202,
      "daily_return": -0.0018720386231884604
    },
    {
      "date": "2023-10-10",
      "nav": 0.8097,
      "daily_return": -0.01282912714658109
    },
    {
      "date": "2023-10-09",
      "nav": 0.8119,
      "daily_return": 0.002753498864404137
    },
    {
      "date": "2023-10-08",
      "nav": 0.8127,
      "daily_return": 0.00090496381458834
    },
    {
      "date": "2023-10-07",
      "nav": 0.8179,
      "daily_return": 0.006409317607960032
    },
    {
      "date": "2023-10-06",
      "nav": 0.8217,
      "daily_return": 0.004680123588619876
    },
    {
      "date": "2023-10-05",
      "nav": 0.8359,
      "daily_return": 0.01725082419140041
    },
    {
      "date": "2023-10-04",
      "nav": 0.8406,
      "daily_return": 0.0056433718183775345
    },
    {
      "date": "2023-10-03",
      "nav": 0.8556,
      "daily_return": 0.017857217320342227
    },
    {
      "date": "2023-10-02",
      "nav": 0.8588,
      "daily_return": 0.003743830165062194
    },
    {
      "date": "2023-10-01",
      "nav": 0.8904,
      "daily_return": 0.03675060964446159
    },
    {
      "date": "2023-09-30",
      "nav": 0.9004,
      "daily_return": 0.011282154795406861
    },
    {
      "date": "2023-09-29",
      "nav": 0.8995,
      "daily_return": -0.0010253427157978696
    },
    {
      "date": "2023-09-28",
      "nav": 0.8959,
      "daily_return": -0.00404806060801052
    },
    {
      "date": "2023-09-27",
      "nav": 0.8853,
      "daily_return": -0.011848308325890986
    },
    {
      "date": "2023-09-26",
      "nav": 0.8991,
      "daily_return": 0.015633859234878242
    },
    {
      "date": "2023-09-25",
      "nav": 0.8958,
      "daily_return": -0.0036347433902411087
    },
    {
      "date": "2023-09-24",
      "nav": 0.888,
      "daily_return": -0.008692186663082847
    },
    {
      "date": "2023-09-23",
      "nav": 0.8738,
      "daily_return": -0.016058851448708528
    },
    {
      "date": "2023-09-22",
      "nav": 0.8883,
      "daily_return": 0.01667596750910417
    },
    {
      "date": "2023-09-21",
      "nav": 0.8898,
      "daily_return": 0.001667249511492865
    }
  ]
}